liangutil/__init__.py
liangutil/kafkautils.py
liangutil/lianglog.py
liangutil/liangutils.py
liangutil/minioutils.py
liangutil/mysqlutils.py
liangutil/redisutils.py
liangutil/requestutils.py
liangutil-0.1.12.dist-info/METADATA
liangutil-0.1.12.dist-info/WHEEL
liangutil-0.1.12.dist-info/top_level.txt
liangutil-0.1.12.dist-info/RECORD
