Metadata-Version: 2.1
Name: liangutil
Version: 0.1.12
Summary: Encapsulate some common tool methods
Home-page: UNKNOWN
Author: LiAng
Author-email: l2545721422@163.com
License: apache 3.0
Keywords: python,utils,windows,mac,linux
Platform: UNKNOWN
Classifier: Topic :: Software Development :: Libraries :: Python Modules
Classifier: Programming Language :: Python :: 3.8
Classifier: Operating System :: Microsoft :: Windows :: Windows 11
Classifier: Natural Language :: Chinese (Simplified)
Requires: datetime
Requires: os
Requires: re
Requires: traceback
Requires: pytz
Requires: platform
Requires: random
Requires: time
Requires: requests
Requires: selenium
Requires: pymysql
Requires: redis
Requires: json
Requires: minio
Requires: wget
Requires: tarfile
Requires: zipfile
Requires: rarfile
Requires: zipfile
Requires: gzip
Requires: shutil
Requires: urllib
Requires: confluent_kafka
